{"bltb52f2e32ba5ccec1":{"locale":"en","audiences":{"group":[{"name":"Asia","_metadata":{"uid":"cs60cc6e012dabff14"},"attributes":[{"key":"travel_type","_metadata":{"uid":"csd40317d0c7f7c0ff"},"value":"relaxation"},{"key":"price_type","_metadata":{"uid":"csa850165c9a0215b2"},"value":"luxury"},{"key":"travel_destination","_metadata":{"uid":"cs738bb350914c3455"},"value":"APAC"}]},{"name":"Europe","_metadata":{"uid":"cs933cdf78af729035"},"attributes":[{"key":"travel_type","_metadata":{"uid":"cs1fcddc945cbb9c8e"},"value":"relaxation"},{"key":"price_type","_metadata":{"uid":"cs13803fe810328a49"},"value":"luxury"},{"key":"travel_destination","_metadata":{"uid":"cs33b8a0fc821297f0"},"value":"EU"}]},{"name":"North America","_metadata":{"uid":"csd3a9385a6e03da55"},"attributes":[{"key":"travel_type","_metadata":{"uid":"cs83f7d95ecf74e4e7"},"value":"relaxation"},{"key":"price_type","_metadata":{"uid":"cs5de5f543e1e5e144"},"value":"luxury"},{"key":"travel_destination","_metadata":{"uid":"cs6aeb0537c65ffe68"},"value":"NA"}]},{"name":"South America","_metadata":{"uid":"csd37e5af3187c00d3"},"attributes":[{"key":"travel_type","_metadata":{"uid":"cs904243333080b567"},"value":"adventure"},{"key":"price_type","_metadata":{"uid":"csabef6852a83c9827"},"value":"budget"},{"key":"travel_destination","_metadata":{"uid":"cs5fcb36cc7a5ff585"},"value":"SA"}]},{"name":"Food and Drink","_metadata":{"uid":"cs9ce3bf3b6d70c204"},"attributes":[{"key":"price_type","_metadata":{"uid":"cs9433e8c5202e8bd2"},"value":"luxury"},{"key":"travel_type","_metadata":{"uid":"cs89489742d2ae4cd0"},"value":"adventure"}]},{"name":"Must See Spots","_metadata":{"uid":"cs9cf2d537632d156c"},"attributes":[{"key":"price_type","_metadata":{"uid":"csa2d14ca5932512f9"},"value":"budget"},{"key":"travel_type","_metadata":{"uid":"csc3a7de270c12a366"},"value":"relaxation"}]},{"name":"Transportation","_metadata":{"uid":"csabdcda565d33136d"},"attributes":[{"key":"price_type","_metadata":{"uid":"csdd505374a16a4a44"},"value":"luxury"},{"key":"travel_type","_metadata":{"uid":"cs14a2c4202cc4ead5"},"value":"adventure"}]}]},"tags":[],"taxonomy_path":"Region","title":"Personalize Config","ACL":{},"uid":"bltb52f2e32ba5ccec1","_version":1,"_in_progress":false,"publish_details":[{"environment":"bltb73a6fe374802283","locale":"en","time":"2025-04-24T11:52:01.034Z","user":"userUID","version":1},{"environment":"bltb377ab306d29e646","locale":"fr","time":"2025-04-24T11:52:01.039Z","user":"userUID","version":1},{"environment":"bltb377ab306d29e646","locale":"es","time":"2025-04-24T11:52:01.098Z","user":"userUID","version":1},{"environment":"bltb377ab306d29e646","locale":"en","time":"2025-04-24T11:52:01.333Z","user":"userUID","version":1},{"environment":"bltb377ab306d29e646","locale":"de","time":"2025-04-24T11:52:01.376Z","user":"userUID","version":1},{"environment":"bltb73a6fe374802283","locale":"es","time":"2025-04-24T11:52:02.138Z","user":"userUID","version":1},{"environment":"bltb73a6fe374802283","locale":"fr","time":"2025-04-24T11:52:02.442Z","user":"userUID","version":1},{"environment":"bltb73a6fe374802283","locale":"de","time":"2025-04-24T11:52:02.461Z","user":"userUID","version":1}]}}